[
	{
		"id": "BEGIN",
		"text": "Начало",
		"inventory_add": "BEGIN_ITEM",
		"images": [
			{"id": "image1", "duration": 1000},
			{"id": "image2", "duration": 1000},
		],
		"audio": ["audio1", "audio2"],
		"background_audio": [
			{"id": "audio3", "start_time":2000, "end_time": 4000},
		],
		"action": "CLICK",
		"decisions": [
			{"id": "option1", "inventoryRequired": ["DEFAULT"]},
			{"id": "option2", "inventoryRequired": ["OPTION_2_ITEM"]},
			{"id": "option3", "inventoryRequired": ["DEFAULT"]},
		]
	},
	{
		"id": "option1",
		"text": "Опция 1",
		"images": [
			{"id": "image3", "duration": 1000},
			{"id": "image4", "duration": 1000},
		],
		"audio": ["audio3"],
		"action": "CLICK",
		"decisions": [
			{"id": "option1", "inventoryRequired": ["DEFAULT"]},
			{"id": "option2", "inventoryRequired": ["DEFAULT"]},
			{"id": "option3", "inventoryRequired": ["DEFAULT"]},
		]
	},
	{
		"id": "option2",
		"text": "Опция 2",
		"inventory_add": "OPTION_2_ITEM",
		"images": [
			{"id": "image5", "duration": 1000},
		],
		"audio": ["audio4", "audio5"],
		"action": "CLICK",
		"decisions": [
			{"id": "option1", "inventoryRequired": ["DEFAULT"]},
			{"id": "BEGIN", "inventoryRequired": ["DEFAULT"]},
			{"id": "option3", "inventoryRequired": ["DEFAULT"]},
		]
	},
	{
		"id": "option3",
		"text": "Опция 3",
		"images": [
			{"id": "image6", "duration": 1000},
			{"id": "image7", "duration": 1000},
		],
		"audio": ["audio6"],
		"action": "CLICK",
		"decisions": [
			{"id": "option1", "inventoryRequired": ["DEFAULT"]},
			{"id": "option2", "inventoryRequired": ["DEFAULT"]},
			{"id": "BEGIN", "inventoryRequired": ["DEFAULT"]},
		]
	}
]